colorprint/__init__.py
colorprint/example.py
colorprint/printer.py
colorprint/unicolor.py
sailist-0.5.dev1.dist-info/LICENSE
sailist-0.5.dev1.dist-info/METADATA
sailist-0.5.dev1.dist-info/WHEEL
sailist-0.5.dev1.dist-info/top_level.txt
sailist-0.5.dev1.dist-info/RECORD
