Metadata-Version: 2.1
Name: sailist
Version: 0.5.dev1
Summary: convert markdown 2 latex code perfactly,support Chinese Language
Home-page: https://github.com/sailist/colorprint
Author: sailist
Author-email: sailist@outlook.com
License: MIT
Keywords: colored text print terminal
Platform: UNKNOWN
Classifier: Development Status :: 3 - Alpha
Classifier: Intended Audience :: Developers
Classifier: Topic :: Software Development :: Build Tools
Classifier: License :: OSI Approved :: MIT License
Classifier: Programming Language :: Python :: 3
Classifier: Programming Language :: Python :: 3.3
Classifier: Programming Language :: Python :: 3.4
Classifier: Programming Language :: Python :: 3.5
